
{"items":[{"name":"ViaTabloidApi.Controllers","href":"ViaTabloidApi.Controllers.html","topicHref":"ViaTabloidApi.Controllers.html","topicUid":"ViaTabloidApi.Controllers","type":"Namespace","items":[{"name":"StoriesController","href":"ViaTabloidApi.Controllers.StoriesController.html","topicHref":"ViaTabloidApi.Controllers.StoriesController.html","topicUid":"ViaTabloidApi.Controllers.StoriesController","type":"Class"}]},{"name":"ViaTabloidApi.Error","href":"ViaTabloidApi.Error.html","topicHref":"ViaTabloidApi.Error.html","topicUid":"ViaTabloidApi.Error","type":"Namespace","items":[{"name":"StoryNotFoundException","href":"ViaTabloidApi.Error.StoryNotFoundException.html","topicHref":"ViaTabloidApi.Error.StoryNotFoundException.html","topicUid":"ViaTabloidApi.Error.StoryNotFoundException","type":"Class"}]},{"name":"ViaTabloidApi.Infrastructure","href":"ViaTabloidApi.Infrastructure.html","topicHref":"ViaTabloidApi.Infrastructure.html","topicUid":"ViaTabloidApi.Infrastructure","type":"Namespace","items":[{"name":"Context","href":"ViaTabloidApi.Infrastructure.Context.html","topicHref":"ViaTabloidApi.Infrastructure.Context.html","topicUid":"ViaTabloidApi.Infrastructure.Context","type":"Class"}]},{"name":"ViaTabloidApi.Infrastructure.Configuration","href":"ViaTabloidApi.Infrastructure.Configuration.html","topicHref":"ViaTabloidApi.Infrastructure.Configuration.html","topicUid":"ViaTabloidApi.Infrastructure.Configuration","type":"Namespace","items":[{"name":"StoryConfiguration","href":"ViaTabloidApi.Infrastructure.Configuration.StoryConfiguration.html","topicHref":"ViaTabloidApi.Infrastructure.Configuration.StoryConfiguration.html","topicUid":"ViaTabloidApi.Infrastructure.Configuration.StoryConfiguration","type":"Class"}]},{"name":"ViaTabloidApi.Middleware","href":"ViaTabloidApi.Middleware.html","topicHref":"ViaTabloidApi.Middleware.html","topicUid":"ViaTabloidApi.Middleware","type":"Namespace","items":[{"name":"ExceptionMiddleware","href":"ViaTabloidApi.Middleware.ExceptionMiddleware.html","topicHref":"ViaTabloidApi.Middleware.ExceptionMiddleware.html","topicUid":"ViaTabloidApi.Middleware.ExceptionMiddleware","type":"Class"}]},{"name":"ViaTabloidApi.Migrations","href":"ViaTabloidApi.Migrations.html","topicHref":"ViaTabloidApi.Migrations.html","topicUid":"ViaTabloidApi.Migrations","type":"Namespace","items":[{"name":"InitialCommit","href":"ViaTabloidApi.Migrations.InitialCommit.html","topicHref":"ViaTabloidApi.Migrations.InitialCommit.html","topicUid":"ViaTabloidApi.Migrations.InitialCommit","type":"Class"}]},{"name":"ViaTabloidApi.Models.DTO","href":"ViaTabloidApi.Models.DTO.html","topicHref":"ViaTabloidApi.Models.DTO.html","topicUid":"ViaTabloidApi.Models.DTO","type":"Namespace","items":[{"name":"CreateStoryDTO","href":"ViaTabloidApi.Models.DTO.CreateStoryDTO.html","topicHref":"ViaTabloidApi.Models.DTO.CreateStoryDTO.html","topicUid":"ViaTabloidApi.Models.DTO.CreateStoryDTO","type":"Class"}]},{"name":"ViaTabloidApi.Resources","href":"ViaTabloidApi.Resources.html","topicHref":"ViaTabloidApi.Resources.html","topicUid":"ViaTabloidApi.Resources","type":"Namespace","items":[{"name":"IStoryRepository","href":"ViaTabloidApi.Resources.IStoryRepository.html","topicHref":"ViaTabloidApi.Resources.IStoryRepository.html","topicUid":"ViaTabloidApi.Resources.IStoryRepository","type":"Interface"},{"name":"StoryRepository","href":"ViaTabloidApi.Resources.StoryRepository.html","topicHref":"ViaTabloidApi.Resources.StoryRepository.html","topicUid":"ViaTabloidApi.Resources.StoryRepository","type":"Class"}]},{"name":"ViaTabloidApi.Services","href":"ViaTabloidApi.Services.html","topicHref":"ViaTabloidApi.Services.html","topicUid":"ViaTabloidApi.Services","type":"Namespace","items":[{"name":"IStoryService","href":"ViaTabloidApi.Services.IStoryService.html","topicHref":"ViaTabloidApi.Services.IStoryService.html","topicUid":"ViaTabloidApi.Services.IStoryService","type":"Interface"},{"name":"StoryService","href":"ViaTabloidApi.Services.StoryService.html","topicHref":"ViaTabloidApi.Services.StoryService.html","topicUid":"ViaTabloidApi.Services.StoryService","type":"Class"}]}],"memberLayout":"SamePage","pdf":true}
